# 泛型

## 什么是泛型？泛型的作用

> 泛型就是参数化类型。就是将具体的类型参数化，类似方法中的变量参数，类型也定义为参数形式（类型形参）。使用的时候传入具体参数（类型实参）。这种参数类型可以用在类、接口跟方法中，分别被称为泛型类，泛型接口、泛型方法。
>
> 例如：`GenericClass<T>`

常用泛型类型变量：

```shell
E：元素(Element)，多用于java集合框架。
K：关键字(Key)
N：数字(Number)
T：类型(Type)
V：值(Value)
```

例如常用的`ArrayList`类：

```java
ArrayList list = new ArrayList();
list.add(1);
list.add("a");
list.add(true);

for(Object o : list) {
    String s = (String)o;  
}
```

如上面这种情况，很明显会发生类型转换异常。在这种情况下就可以使用泛型。

```java
ArrayList<String> strList = new ArrayList<String>();
strList.add("a");
strList.add("b");

for(String s : strList) {
    System.out.println(s);
}
```

这种类型的`List`会在定义的时候就限制类型，明确`List`中保存的数据类型，编译器就会在编译阶段帮我们发现问题。

泛型只在代码编译器有效，如下面代码：

```java
private static void test1() {
    ArrayList<String> strList = new ArrayList<>();
    ArrayList<Integer> intList = new ArrayList<>();
    System.out.println(strList.getClass() == intList.getClass());   //true
}
```

可以看到尽管`strList`跟`intList`使用了不同的泛型，但是它们其实还是同一类型的对象。

这是因为`Java`中是通过类型擦拭实现泛型的，虚拟机对于泛型其实是一无所知的，所有的泛型都是给编译器看的。编译器内部会把所有的类型形参看成是`Object`，再根据类型实参来对数据进行安全的强制转换。例如下面这段代码：

```java
public static void main(String[] args) {
    ArrayList<String> stringList = new ArrayList<>();
    stringList.add("a");

    String s = stringList.get(0);
}
```

通过`javap -c class文件`之后得到：

```java
public static void main(java.lang.String[]);
   Code:
      0: new           #2                  // class java/util/ArrayList
      3: dup
      4: invokespecial #3                  // Method java/util/ArrayList."<init>":()V
      7: astore_1
      8: aload_1
      9: ldc           #4                  // String a
     11: invokevirtual #5                  // Method java/util/ArrayList.add:(Ljava/lang/Object;)Z
     14: pop
     15: aload_1
     16: iconst_0
     17: invokevirtual #6                  // Method java/util/ArrayList.get:(I)Ljava/lang/Object;
     20: checkcast     #7                  // class java/lang/String
     23: astore_2
     24: return
}
```

可以明显的看到，虚拟机看到的最初创建的数组只是一个普通的`ArrayList`，之后取出的时候用了强制类型转换将其转为`String`类型。

## 编写泛型

```java
public class SimpleTypeGenerosity<T> {
    private T first;
    private T second;

    public SimpleTypeGenerosity(T first, T second) {
        this.first = first;
        this.second = second;
    }

    public T getFirst() {
        return first;
    }


    public T getSecond() {
        return second;
    }

    public static <T> SimpleTypeGenerosity<T> create(T first, T second) {
        return new SimpleTypeGenerosity<T>(first, second);
    }

}
```

如上面示例，编写泛型方法只需要在方法名后面\<T\>声明，再把特定的类型替换成声明的T就可以了。

泛型类型\<T\>不能直接用于静态方法，使用的时候需要在`static`修饰符后面加一个\<T\>，实际上静态方法中的类型`T`跟类中声明的`T`已经没有任何关系了。

泛型有时候会定义多种类型，比如`Map`。下面是一个自定义两种泛型的例子：

```java
public class DifferentTypeGenerosity<K, V> {
    private K key;
    private V value;

    public DifferentTypeGenerosity(K key, V value) {
        this.key = key;
        this.value = value;
    }

    public K getKey() {
        return key;
    }

    public void setKey(K key) {
        this.key = key;
    }

    public V getValue() {
        return value;
    }

    public void setValue(V value) {
        this.value = value;
    }
}
```

对于这种泛型类，我们在使用的时候需要指定两个类，这两个类可以是相同的、也可以是不同的。

```java
DifferentTypeGenerosity<String, String> strGenerosity = new DifferentTypeGenerosity<>();
DifferentTypeGenerosity<Integer, String> intGenerosity = new DifferentTypeGenerosity<>();
```

## `Extends`通配符

```java
public void printNumber(SimpleTypeGenerosity<Number> generosity) {
    Number first = generosity.getFirst();
    Number second = generosity.getSecond();
    System.out.println("first=" + first + "--second=" + second);
}
```

上面这个方法需要一个`SimpleTypeGenerosity`类型的对象，指定的泛型类为`Number`

`Integer`类类型也是`Number`，但是当我们试图放入`SimpleTypeGemerosity<Integer>`对象的时候却发现无法编译

```shell
java: 不兼容的类型: com.masq.basic.generosity.SimpleTypeGenerosity<java.lang.Integer>无法转换为com.masq.basic.generosity.SimpleTypeGenerosity<java.lang.Number>
```

原因很明显，尽管`Integer`是`Number`类型的子类，尽管很多时候我们在使用`SimpleTypeGenerosity<Number>`的时候传入的是`Integer`类型的数据，但是`SimpleTypeGenerosity<Integer>`并不是`SimpleTypeGenerosity<Number>`的子类，这种情况如果我们想在上面方法传入`SimpleTypeGenerosity<Integer>`类型是不可能的。

这个时候我们就需要在规定泛型的时候使用`extends`通配符，上面的方法参数可以改写为`SimpleGenerosity<? extends Number>`，规定泛型类型是`Number`或其子类，这样就可以正确传入`SimpleTypeGenerosity<Integer>`类型参数了。

**注意：使用`extends`通配符的时候只能读不能写：**

```java
private static void useList(List<? extends Integer> list) {
    System.out.println(list.get(0));
    list.add(1);
}
```

上面代码在编译的时候就会提示错误，原因是我们不知道`List<? extends Integer>`中的类型是`Integer`还是其子类，所以不能插入数据到`list`中。

## `Super`通配符

同上面示例一样，`SimpleTypeGenerosity<Number>`类型的数据也不能传入参数为`SimpleTypeGenerosity<Integer>`类型的方法中。

跟`extends`通配符相反，`super`通配符规定泛型类型为制定类或者其父类。例如：

```java
public void printNumber(SimpleTypeGenerosity<? super Integer> generosity) {
    Number first = generosity.getFirst();
    Number second = generosity.getSecond();
    System.out.println("first=" + first + "--second=" + second);
}
```

这个时候`printNumber`方法中参数必须是`Integer`或者其父类。

在`<? super T>`中，通过`get`方法无法获取`T`类型的实例(`Object`除外)，允许通过`set`方法传入`T`实例。0

```java
public void testSuper(List<? super Integer> list) {
    Object obj = list.get(0);  
} 
```

如上面代码，通过`get`方法获取数据的时候无法确定数据的类型，所以无法自动转换数据类型，只能通过`Object`来接收数据。

## `PECS`原则

`PECS`原则即(Produce Extends Consumer Super)，该原则解释了何时是哟个`super`何时使用`extends`。如果需要返回`T`，它是生产者，要使用`extends`，如果需要写入`T`，它是消费者，要使用`super`， 例如：

```java
public void copy(List<? extends T> source, List<? super T> target) {
    for (int i=0; i<src.size(); i++) {
        T t = src.get(i);
        dest.add(t);
    }
}
```

## 无限定通配符

Java除了`super`跟`extends`之外，还允许使用无限定通配符`?`。

因为无限定通配符没有`extends`，也没有`super`，因此：

- 不允许`set(T)`方法传入引用(`null`除外)。
- 不允许`T get()`方法获取`T`引用(只能取`Object`引用)。

`List<?>`是所有`List<T>`的超类。
